tempgen/__about__.py
tempgen/__init__.py
tempgen/module.py
tempgen/transforms.py
tempgen/utils.py
tempgen/libs/__init__.py
tempgen/libs/num2t4ru.py
tempgen/parsers/__init__.py
tempgen/parsers/docx.py
tempgen/parsers/ods.py
tempgen/parsers/odt.py
tempgen/parsers/parser.py
tempgen/parsers/plaintext.py
tempgen/parsers/xlsx.py
tempgen/tests/__init__.py
tempgen/tests/helpers.py
tempgen/tests/test_tempgen.py
tempgen-1.1.2.dist-info/LICENSE
tempgen-1.1.2.dist-info/METADATA
tempgen-1.1.2.dist-info/WHEEL
tempgen-1.1.2.dist-info/top_level.txt
tempgen-1.1.2.dist-info/RECORD
