Metadata-Version: 2.1
Name: tempgen
Version: 1.1.2
Summary: Generate files from templates with template entries replaced
Home-page: https://github.com/k5md/Templated-Generator
Author: k5md
Author-email: k-5md@yandex.ru
License: MIT License
Project-URL: Bug Tracker, https://github.com/k5md/Templated-Generator/issues
Platform: UNKNOWN
Classifier: Programming Language :: Python :: 3
Classifier: License :: OSI Approved :: MIT License
Classifier: Operating System :: Microsoft :: Windows
Classifier: Operating System :: Unix
Classifier: Topic :: Utilities
Classifier: Topic :: Documentation
Classifier: Topic :: Office/Business
Classifier: Topic :: Text Processing
Requires-Python: >=3.7
License-File: LICENSE
Requires-Dist: odfpy (>=1.4.1)
Requires-Dist: python-docx (>=0.8.11)
Requires-Dist: python-i18n (>=0.3.9)
Requires-Dist: python-i18n[yaml]
